streamcondor/__init__.py
streamcondor/_version.py
streamcondor/favicons.py
streamcondor/main.py
streamcondor/model.py
streamcondor/monitor.py
streamcondor/resources.py
streamcondor/slhelper.py
streamcondor/assets/app.png
streamcondor/assets/app.svg
streamcondor/assets/sc_b_idle.png
streamcondor/assets/sc_b_idle.svg
streamcondor/assets/sc_b_live.png
streamcondor/assets/sc_b_live.svg
streamcondor/assets/sc_b_off.png
streamcondor/assets/sc_b_off.svg
streamcondor/assets/sc_b_vips.png
streamcondor/assets/sc_b_vips.svg
streamcondor/assets/sc_w_idle.png
streamcondor/assets/sc_w_idle.svg
streamcondor/assets/sc_w_live.png
streamcondor/assets/sc_w_live.svg
streamcondor/assets/sc_w_off.png
streamcondor/assets/sc_w_off.svg
streamcondor/assets/sc_w_vips.png
streamcondor/assets/sc_w_vips.svg
streamcondor/ui/__init__.py
streamcondor/ui/settings.py
streamcondor/ui/stream.py
streamcondor/ui/trayicon.py
streamcondor-1.0.7.dist-info/licenses/LICENSE
streamcondor-1.0.7.dist-info/METADATA
streamcondor-1.0.7.dist-info/WHEEL
streamcondor-1.0.7.dist-info/entry_points.txt
streamcondor-1.0.7.dist-info/top_level.txt
streamcondor-1.0.7.dist-info/RECORD
