Metadata-Version: 2.4
Name: streamcondor
Version: 1.0.7
Summary: A system tray application for monitoring livestreams status
Author: Tarzasai
License-Expression: MIT
Project-URL: Repository, https://github.com/tarzasai/StreamCondor
Project-URL: Issues, https://github.com/tarzasai/StreamCondor/issues
Keywords: stream,tray,monitor,pyqt6
Classifier: Development Status :: 4 - Beta
Classifier: Intended Audience :: End Users/Desktop
Classifier: Programming Language :: Python :: 3
Classifier: Programming Language :: Python :: 3.12
Classifier: Operating System :: OS Independent
Requires-Python: >=3.12
License-File: LICENSE
Requires-Dist: PyQt6>=6.10.0
Requires-Dist: streamlink>=8.0.0
Requires-Dist: requests>=2.32.5
Requires-Dist: beautifulsoup4>=4.14.2
Requires-Dist: Pillow>=12.0.0
Requires-Dist: pyperclip>=1.11.0
Requires-Dist: pydantic>=2.12.5
Dynamic: license-file
